setup.py
pg_warmup/__init__.py
pg_warmup/relation.py
pg_warmup.egg-info/PKG-INFO
pg_warmup.egg-info/SOURCES.txt
pg_warmup.egg-info/dependency_links.txt
pg_warmup.egg-info/entry_points.txt
pg_warmup.egg-info/requires.txt
pg_warmup.egg-info/top_level.txt
pg_warmup/scripts/__init__.py
pg_warmup/scripts/warmup.py