Metadata-Version: 1.1
Name: pg-warmup
Version: 0.2.0
Summary: PostgreSQL warmup tool
Home-page: https://github.com/y-asaba/pg_warmup
Author: Yoshiyuki Asaba
Author-email: ysyk.asaba@gmail.com
License: MIT License
Platform: UNKNOWN
Classifier: Development Status :: 4 - Beta
Classifier: Environment :: Console
Classifier: Intended Audience :: Developers
Classifier: License :: OSI Approved :: MIT License
Classifier: Operating System :: OS Independent
Classifier: Programming Language :: Python
Classifier: Topic :: Database
